[
  {
    "assetPath": "",
    "conditions": {
      "availableForFinish": [
        {
          "completeInSeconds": 0,
          "conditionType": "CounterCreator",
          "counter": {
            "conditions": [
              {
                "bodyPart": [],
                "compareMethod": ">=",
                "conditionType": "Kills",
                "daytime": {
                  "from": 0,
                  "to": 0
                },
                "distance": {
                  "compareMethod": ">=",
                  "value": 0
                },
                "dynamicLocale": false,
                "enemyEquipmentExclusive": [],
                "enemyEquipmentInclusive": [],
                "enemyHealthEffects": [],
                "id": "651413e7ec69c70738548130",
                "resetOnSessionEnd": false,
                "savageRole": [
                  "bossZryachiy"
                ],
                "target": "Savage",
                "value": 1,
                "weapon": [],
                "weaponCaliber": [],
                "weaponModsExclusive": [],
                "weaponModsInclusive": []
              }
            ],
            "id": "651413de80964f5176f559aa"
          },
          "doNotResetIfCounterCompleted": false,
          "dynamicLocale": false,
          "globalQuestCounterId": "",
          "id": "651413de1d1da18970b439e2",
          "index": 0,
          "isNecessary": false,
          "isResetOnConditionFailed": false,
          "oneSessionOnly": false,
          "parentId": "",
          "type": "Completion",
          "value": 15,
          "visibilityConditions": []
        }
      ],
      "fail": []
    },
    "hidden": true,
    "id": "651413e9c31fcb0e163577c9",
    "imageUrl": "/files/achievement/Rare_13.png",
    "index": 99999,
    "instantComplete": false,
    "prefab": "",
    "progressBarEnabled": true,
    "rarity": "Rare",
    "rewards": [],
    "showConditions": false,
    "showNotificationsInGame": false,
    "showProgress": false,
    "side": "Pmc"
  },
  {
    "assetPath": "",
    "conditions": {
      "availableForFinish": [
        {
          "completeInSeconds": 0,
          "conditionType": "CounterCreator",
          "counter": {
            "conditions": [
              {
                "conditionType": "ExitStatus",
                "dynamicLocale": false,
                "id": "65141c2c4240e8676f8180e9",
                "status": [
                  "Killed"
                ]
              }
            ],
            "id": "65141c114a94d94faf76714a"
          },
          "doNotResetIfCounterCompleted": false,
          "dynamicLocale": false,
          "globalQuestCounterId": "",
          "id": "65141c118356939b8a5dcb18",
          "index": 0,
          "isNecessary": false,
          "isResetOnConditionFailed": false,
          "oneSessionOnly": false,
          "parentId": "",
          "type": "Completion",
          "value": 1,
          "visibilityConditions": []
        }
      ],
      "fail": []
    },
    "hidden": true,
    "id": "65141c30ec10ff011f17cc3b",
    "imageUrl": "/files/achievement/Standard_35_1.png",
    "index": 99999,
    "instantComplete": false,
    "prefab": "",
    "progressBarEnabled": false,
    "rarity": "Common",
    "rewards": [],
    "showConditions": false,
    "showNotificationsInGame": false,
    "showProgress": false,
    "side": "Pmc"
  },
  {
    "id": "65141ab70dc723592b0f9482",
    "imageUrl": "/files/achievement/Standard_23.png",
    "assetPath": "",
    "rewards": [],
    "conditions": {
      "availableForFinish": [
        {
          "id": "65141a9264cf3ab72f7e268f",
          "index": 0,
          "dynamicLocale": false,
          "visibilityConditions": [],
          "globalQuestCounterId": "",
          "parentId": "",
          "value": 1,
          "type": "Completion",
          "oneSessionOnly": false,
          "completeInSeconds": 0,
          "doNotResetIfCounterCompleted": false,
          "isResetOnConditionFailed": false,
          "isNecessary": false,
          "counter": {
            "id": "65141a92797468b6dce930d6",
            "conditions": [
              {
                "id": "65141a9cea21eca381b7e45b",
                "dynamicLocale": false,
                "target": "AnyPmc",
                "compareMethod": ">=",
                "value": 1,
                "weapon": [],
                "distance": {
                  "value": 0,
                  "compareMethod": ">="
                },
                "weaponModsInclusive": [],
                "weaponModsExclusive": [],
                "enemyEquipmentInclusive": [],
                "enemyEquipmentExclusive": [],
                "weaponCaliber": [],
                "savageRole": [],
                "bodyPart": [
                  "Head"
                ],
                "daytime": {
                  "from": 0,
                  "to": 0
                },
                "enemyHealthEffects": [],
                "resetOnSessionEnd": false,
                "conditionType": "Kills"
              },
              {
                "id": "65141b1a16b83cee74509f20",
                "dynamicLocale": false,
                "target": [
                  "Buffs_drink_vodka"
                ],
                "conditionType": "HealthBuff"
              }
            ]
          },
          "conditionType": "CounterCreator"
        }
      ],
      "fail": []
    },
    "instantComplete": false,
    "showNotificationsInGame": false,
    "showProgress": false,
    "prefab": "",
    "rarity": "Common",
    "hidden": true,
    "showConditions": false,
    "progressBarEnabled": false,
    "side": "Pmc",
    "index": 99999
  },
  {
    "assetPath": "",
    "conditions": {
      "availableForFinish": [
        {
          "id": "6634c9f2da44501b7a7f7107",
          "index": 0,
          "dynamicLocale": false,
          "visibilityConditions": [],
          "globalQuestCounterId": "",
          "parentId": "",
          "value": 5,
          "type": "Completion",
          "oneSessionOnly": false,
          "completeInSeconds": 0,
          "doNotResetIfCounterCompleted": false,
          "isResetOnConditionFailed": false,
          "isNecessary": false,
          "counter": {
            "id": "6634c9f2859751c06fd4f320",
            "conditions": [
              {
                "id": "6634ca60b2206f345bdd4dac",
                "dynamicLocale": false,
                "target": "Savage",
                "compareMethod": ">=",
                "value": 1,
                "weapon": [
                  "54491bb74bdc2d09088b4567"
                ],
                "distance": {
                  "value": 10000,
                  "compareMethod": ">="
                },
                "weaponModsInclusive": [],
                "weaponModsExclusive": [],
                "enemyEquipmentInclusive": [],
                "enemyEquipmentExclusive": [],
                "weaponCaliber": [],
                "savageRole": [
                  "shooterBTR"
                ],
                "bodyPart": [
                  "Head"
                ],
                "daytime": {
                  "from": 0,
                  "to": 0
                },
                "enemyHealthEffects": [],
                "resetOnSessionEnd": false,
                "conditionType": "Kills"
              }
            ]
          },
          "conditionType": "CounterCreator"
        }
      ],
      "fail": []
    },
    "hidden": true,
    "id": "6634ca69ee506a5c3e61be56",
    "imageUrl": "/files/achievement/S24Q2_ARRS2.png",
    "index": 9997,
    "instantComplete": false,
    "prefab": "",
    "progressBarEnabled": false,
    "rarity": "Legendary",
    "rewards": [
      {
        "availableInGameEditions": [],
        "findInRaid": true,
        "gameMode": [
          "regular",
          "pve"
        ],
        "id": "6706abdfc64e84d18e53f778",
        "illustrationConfig": null,
        "isEncoded": false,
        "isHidden": false,
        "items": [
          {
            "_id": "68547ae84f5b4ef411044e81",
            "_tpl": "6638a5474e92f038531e210e",
            "upd": {
              "SpawnedInSession": true,
              "StackObjectsCount": 1
            }
          }
        ],
        "target": "68547ae84f5b4ef411044e81",
        "type": "Item",
        "unknown": false,
        "value": 1
      }
    ],
    "showConditions": false,
    "showNotificationsInGame": false,
    "showProgress": false,
    "side": "All"
  },
  {
    "assetPath": "",
    "conditions": {
      "availableForFinish": [
        {
          "completeInSeconds": 0,
          "conditionType": "CounterCreator",
          "counter": {
            "conditions": [
              {
                "bodyPart": [],
                "compareMethod": ">=",
                "conditionType": "Kills",
                "daytime": {
                  "from": 0,
                  "to": 0
                },
                "distance": {
                  "compareMethod": ">=",
                  "value": 0
                },
                "dynamicLocale": false,
                "enemyEquipmentExclusive": [],
                "enemyEquipmentInclusive": [],
                "enemyHealthEffects": [],
                "id": "6513f287a87d1a8f970f3ac6",
                "resetOnSessionEnd": false,
                "savageRole": [
                  "bossZryachiy"
                ],
                "target": "Savage",
                "value": 1,
                "weapon": [],
                "weaponCaliber": [],
                "weaponModsExclusive": [],
                "weaponModsInclusive": []
              }
            ],
            "id": "6513f27797103bea6ae0ec6d"
          },
          "doNotResetIfCounterCompleted": false,
          "dynamicLocale": false,
          "globalQuestCounterId": "",
          "id": "6513f2776fcf769579dcb213",
          "index": 0,
          "isNecessary": false,
          "isResetOnConditionFailed": false,
          "oneSessionOnly": false,
          "parentId": "",
          "type": "Completion",
          "value": 1,
          "visibilityConditions": []
        }
      ],
      "fail": []
    },
    "hidden": true,
    "id": "6513f28cb49e3253755f47f3",
    "imageUrl": "/files/achievement/Standard_13.png",
    "index": 99999,
    "instantComplete": false,
    "prefab": "",
    "progressBarEnabled": false,
    "rarity": "Common",
    "rewards": [],
    "showConditions": false,
    "showNotificationsInGame": false,
    "showProgress": false,
    "side": "Pmc"
  },
  {
    "id": "6512f16bde333c33d5127cbc",
    "imageUrl": "/files/achievement/Standard_4.png",
    "assetPath": "",
    "rewards": [],
    "conditions": {
      "availableForFinish": [
        {
          "id": "6512fa32c22df3beb4c784ec",
          "index": 0,
          "dynamicLocale": false,
          "visibilityConditions": [],
          "globalQuestCounterId": "",
          "parentId": "",
          "value": 1,
          "type": "Completion",
          "oneSessionOnly": false,
          "completeInSeconds": 0,
          "doNotResetIfCounterCompleted": false,
          "isResetOnConditionFailed": false,
          "isNecessary": false,
          "counter": {
            "id": "6512fa327820cda3078b7386",
            "conditions": [
              {
                "id": "6512fb2953bb3221a4633b32",
                "dynamicLocale": false,
                "target": "Savage",
                "compareMethod": ">=",
                "value": 1,
                "weapon": [
                  "5fc64ea372b0dd78d51159dc"
                ],
                "distance": {
                  "value": 0,
                  "compareMethod": ">="
                },
                "weaponModsInclusive": [],
                "weaponModsExclusive": [],
                "enemyEquipmentInclusive": [],
                "enemyEquipmentExclusive": [],
                "weaponCaliber": [],
                "savageRole": [
                  "sectantPriest",
                  "sectantWarrior"
                ],
                "bodyPart": [],
                "daytime": {
                  "from": 22,
                  "to": 5
                },
                "enemyHealthEffects": [],
                "resetOnSessionEnd": false,
                "conditionType": "Kills"
              }
            ]
          },
          "conditionType": "CounterCreator"
        }
      ],
      "fail": []
    },
    "instantComplete": false,
    "showNotificationsInGame": false,
    "showProgress": false,
    "prefab": "",
    "rarity": "Common",
    "hidden": true,
    "showConditions": false,
    "progressBarEnabled": false,
    "side": "Pmc",
    "index": 99999
  },
  {
    "id": "65141e37cf2f1c285e606361",
    "imageUrl": "/files/achievement/Standard_30.png",
    "assetPath": "",
    "rewards": [],
    "conditions": {
      "availableForFinish": [
        {
          "id": "65141e43ea19c90e85ad60f5",
          "index": 0,
          "dynamicLocale": false,
          "visibilityConditions": [],
          "globalQuestCounterId": "",
          "parentId": "",
          "value": 1,
          "type": "Completion",
          "oneSessionOnly": false,
          "completeInSeconds": 0,
          "doNotResetIfCounterCompleted": false,
          "isResetOnConditionFailed": false,
          "isNecessary": false,
          "counter": {
            "id": "65141e43228fae16452d4a5f",
            "conditions": [
              {
                "id": "65141e89290391d51161d574",
                "dynamicLocale": false,
                "target": "achiv_office",
                "value": 1,
                "conditionType": "VisitPlace"
              }
            ]
          },
          "conditionType": "CounterCreator"
        }
      ],
      "fail": []
    },
    "instantComplete": false,
    "showNotificationsInGame": false,
    "showProgress": false,
    "prefab": "",
    "rarity": "Common",
    "hidden": true,
    "showConditions": false,
    "progressBarEnabled": false,
    "side": "Pmc",
    "index": 99999
  },
  {
    "assetPath": "",
    "conditions": {
      "availableForFinish": [
        {
          "completeInSeconds": 0,
          "conditionType": "CounterCreator",
          "counter": {
            "conditions": [
              {
                "bodyPart": [],
                "compareMethod": ">=",
                "conditionType": "Kills",
                "daytime": {
                  "from": 0,
                  "to": 0
                },
                "distance": {
                  "compareMethod": ">=",
                  "value": 0
                },
                "dynamicLocale": false,
                "enemyEquipmentExclusive": [],
                "enemyEquipmentInclusive": [],
                "enemyHealthEffects": [],
                "id": "6514184d03e721757ca5d27f",
                "resetOnSessionEnd": false,
                "savageRole": [],
                "target": "AnyPmc",
                "value": 1,
                "weapon": [],
                "weaponCaliber": [],
                "weaponModsExclusive": [],
                "weaponModsInclusive": []
              }
            ],
            "id": "6514184336f01da63f602162"
          },
          "doNotResetIfCounterCompleted": false,
          "dynamicLocale": false,
          "globalQuestCounterId": "",
          "id": "651418430ab21e2a907ab76f",
          "index": 0,
          "isNecessary": false,
          "isResetOnConditionFailed": false,
          "oneSessionOnly": true,
          "parentId": "",
          "type": "Completion",
          "value": 7,
          "visibilityConditions": []
        }
      ],
      "fail": []
    },
    "hidden": true,
    "id": "6514184ec31fcb0e163577d2",
    "imageUrl": "/files/achievement/Rare_20.png",
    "index": 99999,
    "instantComplete": false,
    "prefab": "",
    "progressBarEnabled": false,
    "rarity": "Rare",
    "rewards": [],
    "showConditions": false,
    "showNotificationsInGame": false,
    "showProgress": false,
    "side": "Pmc"
  },
  {
    "assetPath": "",
    "conditions": {
      "availableForFinish": [
        {
          "completeInSeconds": 0,
          "conditionType": "CounterCreator",
          "counter": {
            "conditions": [
              {
                "conditionType": "VisitPlace",
                "dynamicLocale": false,
                "id": "65141ed42b9fde0025039a2e",
                "target": "achiv_plane",
                "value": 1
              }
            ],
            "id": "65141eccc68987ea3789392f"
          },
          "doNotResetIfCounterCompleted": false,
          "dynamicLocale": false,
          "globalQuestCounterId": "",
          "id": "65141ecc4f29c8d1bc7d66ad",
          "index": 0,
          "isNecessary": false,
          "isResetOnConditionFailed": false,
          "oneSessionOnly": false,
          "parentId": "",
          "type": "Completion",
          "value": 1,
          "visibilityConditions": []
        }
      ],
      "fail": []
    },
    "hidden": true,
    "id": "65141eb5c31fcb0e163577dd",
    "imageUrl": "/files/achievement/Standard_31.png",
    "index": 99999,
    "instantComplete": false,
    "prefab": "",
    "progressBarEnabled": false,
    "rarity": "Common",
    "rewards": [],
    "showConditions": false,
    "showNotificationsInGame": false,
    "showProgress": false,
    "side": "Pmc"
  },
  {
    "assetPath": "",
    "conditions": {
      "availableForFinish": [
        {
          "completeInSeconds": 0,
          "conditionType": "CounterCreator",
          "counter": {
            "conditions": [
              {
                "bodyPart": [
                  "Head"
                ],
                "compareMethod": ">=",
                "conditionType": "Kills",
                "daytime": {
                  "from": 0,
                  "to": 0
                },
                "distance": {
                  "compareMethod": ">=",
                  "value": 500
                },
                "dynamicLocale": false,
                "enemyEquipmentExclusive": [],
                "enemyEquipmentInclusive": [],
                "enemyHealthEffects": [],
                "id": "6514174ab2cce6e3be28fd12",
                "resetOnSessionEnd": false,
                "savageRole": [],
                "target": "AnyPmc",
                "value": 1,
                "weapon": [],
                "weaponCaliber": [],
                "weaponModsExclusive": [],
                "weaponModsInclusive": []
              }
            ],
            "id": "65141720df1f2d3bd55460d6"
          },
          "doNotResetIfCounterCompleted": false,
          "dynamicLocale": false,
          "globalQuestCounterId": "",
          "id": "6514172005d663354394968e",
          "index": 0,
          "isNecessary": false,
          "isResetOnConditionFailed": false,
          "oneSessionOnly": false,
          "parentId": "",
          "type": "Completion",
          "value": 1,
          "visibilityConditions": []
        }
      ],
      "fail": []
    },
    "hidden": true,
    "id": "6514174fb1c08b0feb216d73",
    "imageUrl": "/files/achievement/Standard_16.png",
    "index": 99999,
    "instantComplete": false,
    "prefab": "",
    "progressBarEnabled": false,
    "rarity": "Common",
    "rewards": [],
    "showConditions": false,
    "showNotificationsInGame": false,
    "showProgress": false,
    "side": "Pmc"
  },
  {
    "assetPath": "",
    "conditions": {
      "availableForFinish": [
        {
          "id": "6527f2f2c4d6004e4edbba06",
          "index": 0,
          "dynamicLocale": false,
          "visibilityConditions": [],
          "globalQuestCounterId": "",
          "parentId": "",
          "value": 1,
          "type": "Completion",
          "oneSessionOnly": false,
          "completeInSeconds": 0,
          "doNotResetIfCounterCompleted": false,
          "isResetOnConditionFailed": false,
          "isNecessary": false,
          "counter": {
            "id": "6527f2f297f3f0094887163e",
            "conditions": [
              {
                "id": "6527f3011dd276a0de4cbec2",
                "dynamicLocale": false,
                "target": "Savage",
                "compareMethod": ">=",
                "value": 1,
                "weapon": [],
                "distance": {
                  "value": 0,
                  "compareMethod": ">="
                },
                "weaponModsInclusive": [],
                "weaponModsExclusive": [],
                "enemyEquipmentInclusive": [],
                "enemyEquipmentExclusive": [],
                "weaponCaliber": [],
                "savageRole": [],
                "bodyPart": [],
                "daytime": {
                  "from": 0,
                  "to": 0
                },
                "enemyHealthEffects": [],
                "resetOnSessionEnd": false,
                "conditionType": "Kills"
              }
            ]
          },
          "conditionType": "CounterCreator"
        }
      ],
      "fail": []
    },
    "hidden": true,
    "id": "6527ee4a647c29201011defe",
    "imageUrl": "/files/achievement/Standard_43.png",
    "index": 99999,
    "instantComplete": false,
    "prefab": "",
    "progressBarEnabled": false,
    "rarity": "Common",
    "rewards": [],
    "showConditions": false,
    "showNotificationsInGame": false,
    "showProgress": false,
    "side": "Savage"
  },
  {
    "id": "676094451fec2f7426093be6",
    "imageUrl": "/files/achievement/676093bf2a7be2d1f706f0ec.png",
    "assetPath": "",
    "rewards": [],
    "conditions": {
      "availableForFinish": [
        {
          "id": "67609450d8c6c5112221a710",
          "index": 0,
          "dynamicLocale": false,
          "visibilityConditions": [],
          "globalQuestCounterId": "",
          "parentId": "",
          "value": 100000,
          "type": "Completion",
          "oneSessionOnly": false,
          "completeInSeconds": 0,
          "doNotResetIfCounterCompleted": false,
          "isResetOnConditionFailed": false,
          "isNecessary": false,
          "counter": {
            "id": "676094504fc891ced300dc7f",
            "conditions": [
              {
                "id": "6760947663e90bab925dab41",
                "dynamicLocale": false,
                "target": "Savage",
                "compareMethod": ">=",
                "value": 10000,
                "weapon": [
                  "54491bb74bdc2d09088b4567"
                ],
                "distance": {
                  "value": 10000,
                  "compareMethod": ">="
                },
                "weaponModsInclusive": [],
                "weaponModsExclusive": [],
                "enemyEquipmentInclusive": [],
                "enemyEquipmentExclusive": [],
                "weaponCaliber": [],
                "savageRole": [
                  "shooterBTR"
                ],
                "bodyPart": [
                  "Head"
                ],
                "daytime": {
                  "from": 0,
                  "to": 0
                },
                "enemyHealthEffects": [],
                "resetOnSessionEnd": false,
                "conditionType": "Kills"
              }
            ]
          },
          "conditionType": "CounterCreator"
        }
      ],
      "fail": []
    },
    "instantComplete": false,
    "showNotificationsInGame": false,
    "showProgress": false,
    "prefab": "",
    "rarity": "Legendary",
    "hidden": true,
    "showConditions": false,
    "progressBarEnabled": false,
    "side": "All",
    "index": 99999
  },
  {
    "id": "6634cae870af846d2868dada",
    "imageUrl": "/files/achievement/S24Q2_ARRS3.png",
    "assetPath": "",
    "rewards": [
      {
        "id": "6707ed1ad2e18b0e6a31ee76",
        "unknown": false,
        "gameMode": [
          "regular",
          "pve"
        ],
        "availableInGameEditions": [],
        "illustrationConfig": null,
        "isHidden": false,
        "target": "68547ae84f5b4ef411044e92",
        "value": 1,
        "isEncoded": false,
        "findInRaid": true,
        "items": [
          {
            "_id": "68547ae84f5b4ef411044e92",
            "_tpl": "6638a5474e92f038531e210e",
            "upd": {
              "SpawnedInSession": true,
              "StackObjectsCount": 1
            }
          }
        ],
        "type": "Item"
      }
    ],
    "conditions": {
      "availableForFinish": [
        {
          "id": "6634caf263da6c6a4304992c",
          "index": 0,
          "dynamicLocale": false,
          "visibilityConditions": [],
          "globalQuestCounterId": "",
          "parentId": "",
          "value": 5,
          "type": "Completion",
          "oneSessionOnly": false,
          "completeInSeconds": 0,
          "doNotResetIfCounterCompleted": false,
          "isResetOnConditionFailed": false,
          "isNecessary": false,
          "counter": {
            "id": "6634caf2073e81109cb49b7b",
            "conditions": [
              {
                "id": "6634cb14d1dc9e283b46e58d",
                "dynamicLocale": false,
                "target": "Savage",
                "compareMethod": ">=",
                "value": 1,
                "weapon": [
                  "54491bb74bdc2d09088b4567"
                ],
                "distance": {
                  "value": 10000,
                  "compareMethod": ">="
                },
                "weaponModsInclusive": [],
                "weaponModsExclusive": [],
                "enemyEquipmentInclusive": [],
                "enemyEquipmentExclusive": [],
                "weaponCaliber": [],
                "savageRole": [
                  "shooterBTR"
                ],
                "bodyPart": [],
                "daytime": {
                  "from": 0,
                  "to": 0
                },
                "enemyHealthEffects": [],
                "resetOnSessionEnd": false,
                "conditionType": "Kills"
              }
            ]
          },
          "conditionType": "CounterCreator"
        }
      ],
      "fail": []
    },
    "instantComplete": false,
    "showNotificationsInGame": false,
    "showProgress": false,
    "prefab": "",
    "rarity": "Legendary",
    "hidden": true,
    "showConditions": false,
    "progressBarEnabled": false,
    "side": "All",
    "index": 9998
  },
  {
    "id": "676091c0f457869a94017a23",
    "imageUrl": "/files/achievement/676093b76e682163da028a28.png",
    "assetPath": "",
    "rewards": [],
    "conditions": {
      "availableForFinish": [
        {
          "id": "6760919bea0b8ae795c9cf71",
          "index": 0,
          "dynamicLocale": false,
          "visibilityConditions": [],
          "globalQuestCounterId": "",
          "parentId": "",
          "value": 1000000,
          "type": "Completion",
          "oneSessionOnly": false,
          "completeInSeconds": 1,
          "doNotResetIfCounterCompleted": false,
          "isResetOnConditionFailed": false,
          "isNecessary": false,
          "counter": {
            "id": "6760919b08a6df50916f00c9",
            "conditions": [
              {
                "id": "676091b72c3f5a17880358f4",
                "dynamicLocale": false,
                "target": "Savage",
                "compareMethod": ">=",
                "value": 100000,
                "weapon": [
                  "54491bb74bdc2d09088b4567"
                ],
                "distance": {
                  "value": 10000,
                  "compareMethod": ">="
                },
                "weaponModsInclusive": [],
                "weaponModsExclusive": [],
                "enemyEquipmentInclusive": [],
                "enemyEquipmentExclusive": [],
                "weaponCaliber": [],
                "savageRole": [
                  "shooterBTR"
                ],
                "bodyPart": [
                  "Head"
                ],
                "daytime": {
                  "from": 0,
                  "to": 0
                },
                "enemyHealthEffects": [],
                "resetOnSessionEnd": false,
                "conditionType": "Kills"
              }
            ]
          },
          "conditionType": "CounterCreator"
        }
      ],
      "fail": []
    },
    "instantComplete": false,
    "showNotificationsInGame": false,
    "showProgress": false,
    "prefab": "",
    "rarity": "Legendary",
    "hidden": true,
    "showConditions": false,
    "progressBarEnabled": false,
    "side": "All",
    "index": 99999
  },
  {
    "id": "6634c8886e083a141f4aa3f4",
    "imageUrl": "/files/achievement/S24Q2_ARRS1.png",
    "assetPath": "",
    "rewards": [
      {
        "id": "6706abfa3b44ddfcf586ab19",
        "unknown": false,
        "gameMode": [
          "regular",
          "pve"
        ],
        "availableInGameEditions": [],
        "illustrationConfig": null,
        "isHidden": false,
        "target": "68547ae84f5b4ef411044ea2",
        "value": 1,
        "isEncoded": false,
        "findInRaid": true,
        "items": [
          {
            "_id": "68547ae84f5b4ef411044ea2",
            "_tpl": "6638a5474e92f038531e210e",
            "upd": {
              "SpawnedInSession": true,
              "StackObjectsCount": 1
            }
          }
        ],
        "type": "Item"
      }
    ],
    "conditions": {
      "availableForFinish": [
        {
          "id": "6634c942234642e3f2cb3623",
          "index": 0,
          "dynamicLocale": false,
          "visibilityConditions": [],
          "globalQuestCounterId": "",
          "parentId": "",
          "value": 5,
          "type": "Completion",
          "oneSessionOnly": false,
          "completeInSeconds": 0,
          "doNotResetIfCounterCompleted": false,
          "isResetOnConditionFailed": false,
          "isNecessary": false,
          "counter": {
            "id": "6634c942b584208879dcebe7",
            "conditions": [
              {
                "id": "6634c96714aea75fd7ee417f",
                "dynamicLocale": false,
                "target": "Savage",
                "compareMethod": ">=",
                "value": 1,
                "weapon": [
                  "54491bb74bdc2d09088b4567"
                ],
                "distance": {
                  "value": 10000,
                  "compareMethod": ">="
                },
                "weaponModsInclusive": [],
                "weaponModsExclusive": [],
                "enemyEquipmentInclusive": [],
                "enemyEquipmentExclusive": [],
                "weaponCaliber": [],
                "savageRole": [
                  "shooterBTR"
                ],
                "bodyPart": [],
                "daytime": {
                  "from": 0,
                  "to": 0
                },
                "enemyHealthEffects": [],
                "resetOnSessionEnd": false,
                "conditionType": "Kills"
              }
            ]
          },
          "conditionType": "CounterCreator"
        }
      ],
      "fail": []
    },
    "instantComplete": false,
    "showNotificationsInGame": false,
    "showProgress": false,
    "prefab": "",
    "rarity": "Legendary",
    "hidden": true,
    "showConditions": false,
    "progressBarEnabled": false,
    "side": "All",
    "index": 9996
  },
  {
    "id": "67fce0c2f18dc20eae02240b",
    "imageUrl": "/files/achievement/6821f5e71d89b4e49305a478.png",
    "assetPath": "",
    "rewards": [],
    "conditions": {
      "availableForFinish": [
        {
          "id": "67fcdfccb2d35ad46a7a706f",
          "index": 0,
          "dynamicLocale": false,
          "visibilityConditions": [],
          "globalQuestCounterId": "",
          "parentId": "",
          "value": 1,
          "type": "Elimination",
          "oneSessionOnly": false,
          "completeInSeconds": 0,
          "doNotResetIfCounterCompleted": false,
          "isResetOnConditionFailed": false,
          "isNecessary": false,
          "counter": {
            "id": "67fcdfcc62dc6fc00ad6cba7",
            "conditions": [
              {
                "id": "67fce0795bafaf46dde7fdff",
                "dynamicLocale": false,
                "target": "Savage",
                "compareMethod": ">=",
                "value": 1,
                "weapon": [
                  "676bf44c5539167c3603e869"
                ],
                "distance": {
                  "value": 0,
                  "compareMethod": ">="
                },
                "weaponModsInclusive": [],
                "weaponModsExclusive": [],
                "enemyEquipmentInclusive": [],
                "enemyEquipmentExclusive": [],
                "weaponCaliber": [],
                "savageRole": [
                  "sectantPriest",
                  "sectantWarrior"
                ],
                "bodyPart": [],
                "daytime": {
                  "from": 0,
                  "to": 0
                },
                "enemyHealthEffects": [],
                "resetOnSessionEnd": false,
                "conditionType": "Kills"
              }
            ]
          },
          "conditionType": "CounterCreator"
        }
      ],
      "fail": []
    },
    "instantComplete": false,
    "showNotificationsInGame": false,
    "showProgress": false,
    "prefab": "",
    "rarity": "Rare",
    "hidden": true,
    "showConditions": false,
    "progressBarEnabled": false,
    "side": "Pmc",
    "index": 3300
  }
]
